lambdaconda/__init__.py
lambdaconda/lambdaconda.py
lambdaconda-0.0.3.dist-info/LICENSE
lambdaconda-0.0.3.dist-info/METADATA
lambdaconda-0.0.3.dist-info/WHEEL
lambdaconda-0.0.3.dist-info/top_level.txt
lambdaconda-0.0.3.dist-info/RECORD
