Metadata-Version: 2.1
Name: lambdaconda
Version: 0.0.3
Summary: Playing around with an AWS lambda library
Home-page: https://github.com/rileymathews/lambdaconda
Author: Riley Mathews
Author-email: rileymathews80@gmail.com
License: UNKNOWN
Platform: UNKNOWN
Classifier: Programming Language :: Python :: 3
Classifier: License :: OSI Approved :: MIT License
Classifier: Operating System :: OS Independent
Requires-Python: >=3.6
